odoo/addons/easy_my_coop_connector/README.rst
odoo/addons/easy_my_coop_connector/__init__.py
odoo/addons/easy_my_coop_connector/__manifest__.py
odoo/addons/easy_my_coop_connector/components/__init__.py
odoo/addons/easy_my_coop_connector/components/abstract_emc_adapter.py
odoo/addons/easy_my_coop_connector/components/account_invoice_adapter.py
odoo/addons/easy_my_coop_connector/components/account_payment_adapter.py
odoo/addons/easy_my_coop_connector/components/emc_backend.py
odoo/addons/easy_my_coop_connector/components/emc_bindings.py
odoo/addons/easy_my_coop_connector/components/subscription_request_adapter.py
odoo/addons/easy_my_coop_connector/data/cron.xml
odoo/addons/easy_my_coop_connector/demo/demo.xml
odoo/addons/easy_my_coop_connector/i18n/easy_my_coop_connector.pot
odoo/addons/easy_my_coop_connector/models/__init__.py
odoo/addons/easy_my_coop_connector/models/account_account.py
odoo/addons/easy_my_coop_connector/models/account_invoice.py
odoo/addons/easy_my_coop_connector/models/account_journal.py
odoo/addons/easy_my_coop_connector/models/account_payment.py
odoo/addons/easy_my_coop_connector/models/subscription_request.py
odoo/addons/easy_my_coop_connector/readme/CONTRIBUTORS.rst
odoo/addons/easy_my_coop_connector/readme/DESCRIPTION.rst
odoo/addons/easy_my_coop_connector/readme/ROADMAP.rst
odoo/addons/easy_my_coop_connector/readme/USAGE.rst
odoo/addons/easy_my_coop_connector/security/ir.model.access.csv
odoo/addons/easy_my_coop_connector/static/description/index.html
odoo/addons/easy_my_coop_connector/tests/__init__.py
odoo/addons/easy_my_coop_connector/tests/test_adapters.py
odoo/addons/easy_my_coop_connector/tests/test_data.py
odoo/addons/easy_my_coop_connector/tests/test_payment.py
odoo/addons/easy_my_coop_connector/tests/test_subscription_request.py
odoo/addons/easy_my_coop_connector/views/actions.xml
odoo/addons/easy_my_coop_connector/views/emc_backend.xml
odoo/addons/easy_my_coop_connector/views/emc_bindings.xml
odoo12_addon_easy_my_coop_connector-12.0.0.0.1.99.dev38.dist-info/METADATA
odoo12_addon_easy_my_coop_connector-12.0.0.0.1.99.dev38.dist-info/WHEEL
odoo12_addon_easy_my_coop_connector-12.0.0.0.1.99.dev38.dist-info/top_level.txt
odoo12_addon_easy_my_coop_connector-12.0.0.0.1.99.dev38.dist-info/RECORD
